rds_log-1.0.6.dist-info/DESCRIPTION.rst
rds_log-1.0.6.dist-info/entry_points.txt
rds_log-1.0.6.dist-info/METADATA
rds_log-1.0.6.dist-info/metadata.json
rds_log-1.0.6.dist-info/RECORD
rds_log-1.0.6.dist-info/top_level.txt
rds_log-1.0.6.dist-info/WHEEL
_rds_log/local_log.py
_rds_log/rds.py
_rds_log/__init__.py
_rds_log/commands/rds_log_stream.py
_rds_log/commands/__init__.py
