Metadata-Version: 2.0
Name: rds-log
Version: 1.0.6
Summary: A utility to download AWS RDS logs
Home-page: https://github.com/pelme/rds-log
Author: Andreas Pelme
Author-email: andreas@pelme.se
License: UNKNOWN
Platform: UNKNOWN
Classifier: Development Status :: 5 - Production/Stable
Classifier: Programming Language :: Python :: 3.4
Classifier: Programming Language :: Python :: 3.6
Requires-Dist: boto3 (==1.4.7)
Requires-Dist: click (==5.1)
